CHANGES
MANIFEST.in
README.md
setup.cfg
setup.py
src/django_page_exporter.egg-info/PKG-INFO
src/django_page_exporter.egg-info/SOURCES.txt
src/django_page_exporter.egg-info/dependency_links.txt
src/django_page_exporter.egg-info/requires.txt
src/django_page_exporter.egg-info/top_level.txt
src/page_exporter/__init__.py
src/page_exporter/config.py
src/page_exporter/urls.py
src/page_exporter/utils.py
src/page_exporter/views.py
src/page_exporter/__pycache__/__init__.cpython-36.pyc
src/page_exporter/__pycache__/__init__.cpython-38.pyc
src/page_exporter/scripts/capture.js
src/page_exporter/scripts/print.js
src/requirements/develop.pip
src/requirements/install.any.pip
src/requirements/install.py2.pip
src/requirements/install.py3.pip
src/requirements/testing.pip