Metadata-Version: 2.1
Name: django-page-exporter
Version: 0.6.3
Summary: Django Page Exporter
Home-page: https://github.com/marcoimme/django-page-exporter/
Author: Marco Immediato
Author-email: marcoimme@gmail.com
License: MIT
Platform: linux
Classifier: Environment :: Web Environment
Classifier: Framework :: Django
Classifier: Framework :: Django :: 1.11
Classifier: Framework :: Django :: 2.0
Classifier: Operating System :: OS Independent
Classifier: Programming Language :: Python :: 2.7
Classifier: Programming Language :: Python :: 3.5
Classifier: Intended Audience :: Developers
Provides-Extra: test
Provides-Extra: dev
